datastructurepack/__init__.py
datastructurepack/__main__.py
datastructurepack/datastructure.py
datastructurepack_deskent-1.2.0.dist-info/LICENSE
datastructurepack_deskent-1.2.0.dist-info/METADATA
datastructurepack_deskent-1.2.0.dist-info/WHEEL
datastructurepack_deskent-1.2.0.dist-info/top_level.txt
datastructurepack_deskent-1.2.0.dist-info/RECORD
