Metadata-Version: 2.1
Name: datastructurepack-deskent
Version: 1.2.0
Summary: Datastorage
Author: Deskent
Classifier: Programming Language :: Python :: 3
Classifier: License :: OSI Approved :: MIT License
Classifier: Operating System :: OS Independent
Requires-Python: >=3.7
License-File: LICENSE
Requires-Dist: pydantic (==1.9.1)
